uniparser_morph/ErrorHandler.py
uniparser_morph/__init__.py
uniparser_morph/analyze.py
uniparser_morph/cg_disambiguate.py
uniparser_morph/clitic.py
uniparser_morph/common_functions.py
uniparser_morph/derivations.py
uniparser_morph/grammar.py
uniparser_morph/lex_rule.py
uniparser_morph/lexeme.py
uniparser_morph/morph_fst.py
uniparser_morph/morph_parser.py
uniparser_morph/paradigm.py
uniparser_morph/periphrastic.py
uniparser_morph/reduplication.py
uniparser_morph/stem_conversion.py
uniparser_morph/wordform.py
uniparser_morph/yamlReader.py
uniparser_morph-2.9.4.dist-info/LICENSE
uniparser_morph-2.9.4.dist-info/METADATA
uniparser_morph-2.9.4.dist-info/WHEEL
uniparser_morph-2.9.4.dist-info/top_level.txt
uniparser_morph-2.9.4.dist-info/RECORD
