Metadata-Version: 2.1
Name: uniparser-morph
Version: 2.9.4
Summary: Rule-based, linguist-friendly (and rather slow) morphological analysis
Home-page: https://github.com/timarkh/uniparser-morph
Author: Timofey Arkhangelskiy
Author-email: timarkh@gmail.com
Project-URL: Documentation, https://uniparser-morph.readthedocs.io/en/latest/
Project-URL: Source Code, https://github.com/timarkh/uniparser-morph
Project-URL: Bug Tracker, https://github.com/timarkh/uniparser-morph/issues
Classifier: Programming Language :: Python :: 3
Classifier: License :: OSI Approved :: MIT License
Classifier: Operating System :: OS Independent
Classifier: Intended Audience :: Science/Research
Classifier: Topic :: Text Processing :: Linguistic
Requires-Python: >=3.5
License-File: LICENSE
Requires-Dist: textdistance>=4.0.0
